[
  {"palabra": "Andragogía", "prohibidas": ["Adultos", "Enseñanza", "Aprendizaje", "Educación", "Pedagogía"]},
  {"palabra": "Constructivismo", "prohibidas": ["Construir", "Experiencias", "Alumno", "Conocimiento", "Activo"]},
  {"palabra": "Zona de Desarrollo Próximo (ZDP)", "prohibidas": ["Vygotsky", "Distancia", "Ayuda", "Capacidad", "Solo"]},
  {"palabra": "Aprendizaje Significativo", "prohibidas": ["Ausubel", "Relacionar", "Conocimientos", "Saberes", "Nuevo"]},
  {"palabra": "Currículum Oculto", "prohibidas": ["Valores", "Normas", "Actitudes", "Escuela", "Programa"]},
  {"palabra": "Metacognición", "prohibidas": ["Pensamiento", "Reflexionar", "Controlar", "Proceso", "Aprender"]},
  {"palabra": "Transversalidad", "prohibidas": ["Temas", "Asignaturas", "Medio ambiente", "Valores", "Género"]},
  {"palabra": "Escuela Nueva", "prohibidas": ["Movimiento", "Pedagógico", "Alumno", "Experiencia", "Actividad"]},
  {"palabra": "Aprendizaje Basado en Problemas (ABP)", "prohibidas": ["Problemas", "Estrategia", "Resolver", "Situaciones", "Estudiantes"]},
  {"palabra": "Inteligencias Múltiples", "prohibidas": ["Gardner", "Inteligencia", "Tipos", "Musical", "Matemática"]},
  {"palabra": "Inclusión Educativa", "prohibidas": ["Acceso", "Participación", "Estudiantes", "Discriminación", "Permanencia"]},
  {"palabra": "Enseñanza Diferenciada", "prohibidas": ["Contenidos", "Actividades", "Evaluación", "Necesidades", "Individuales"]},
  {"palabra": "Didáctica Crítica", "prohibidas": ["Transformar", "Realidad", "Social", "Enseñanza", "Corriente"]},
  {"palabra": "Heteroevaluación", "prohibidas": ["Evaluación", "Alumno", "Externa", "Docente", "Tutor"]},
  {"palabra": "Autoevaluación", "prohibidas": ["Estudiante", "Propio", "Aprendizaje", "Desempeño", "Proceso"]},
  {"palabra": "Cognición Distribuida", "prohibidas": ["Compartir", "Conocimiento", "Individuos", "Herramientas", "Contextos"]},
  {"palabra": "Mediación Pedagógica", "prohibidas": ["Docente", "Guía", "Facilitar", "Aprendizaje", "Intervención"]},
  {"palabra": "Epistemología de la Educación", "prohibidas": ["Conocimiento", "Valida", "Construye", "Estudia", "Educación"]},
  {"palabra": "Escuela Inclusiva", "prohibidas": ["Diversidad", "Barreras", "Aprendizaje", "Modelo", "Educativo"]},
  {"palabra": "Neuroeducación", "prohibidas": ["Cerebro", "Neurociencia", "Psicología", "Pedagogía", "Procesos"]}
]
